env_maker/__init__.py
env_maker/main.py
env_maker/utils.py
env_maker-0.1.0.dist-info/licenses/LICENSE
env_maker-0.1.0.dist-info/METADATA
env_maker-0.1.0.dist-info/WHEEL
env_maker-0.1.0.dist-info/entry_points.txt
env_maker-0.1.0.dist-info/top_level.txt
env_maker-0.1.0.dist-info/RECORD
