Metadata-Version: 2.4
Name: env-maker
Version: 0.1.0
Summary: A tool to manage .env files, create examples, and convert to other formats.
Author-email: Juan José Sánchez <pip@jjsm.science>
License:                     GNU GENERAL PUBLIC LICENSE
Project-URL: Repository, https://github.com/jj-sm/env-maker
Classifier: Programming Language :: Python :: 3
Classifier: License :: OSI Approved :: MIT License
Classifier: Operating System :: OS Independent
Requires-Python: >=3.8
License-File: LICENSE
Requires-Dist: PyYAML
Requires-Dist: tomli-w
Dynamic: license-file
